Workbook

Sheet Summary
A1: 15-YEAR INTEGRATED FINANCIAL MODEL
A2: USD (thousands) | B2: 2024 | C2: 2025 | D2: 2026 | E2: 2027 | F2: 2028 | G2: 2029 | H2: 2030 | I2: 2031 | J2: 2032 | K2: 2033 | L2: 2034 | M2: 2035 | N2: 2036 | O2: 2037 | P2: 2038
A3: Revenue | B3: ='Income Statement'!B4 | C3: ='Income Statement'!C4 | D3: ='Income Statement'!D4 | E3: ='Income Statement'!E4 | F3: ='Income Statement'!F4 | G3: ='Income Statement'!G4 | H3: ='Income Statement'!H4 | I3: ='Income Statement'!I4 | ... P3: ='Income Statement'!P4
A4: Gross Profit | B4: ='Income Statement'!B7 | C4: ='Income Statement'!C7 | D4: ='Income Statement'!D7 | E4: ='Income Statement'!E7 | F4: ='Income Statement'!F7 | G4: ='Income Statement'!G7 | H4: ='Income Statement'!H7 | I4: ='Income Statement'!I7 | ... P4: ='Income Statement'!P7
A5: EBIT | B5: ='Income Statement'!B13 | C5: ='Income Statement'!C13 | D5: ='Income Statement'!D13 | E5: ='Income Statement'!E13 | F5: ='Income Statement'!F13 | G5: ='Income Statement'!G13 | H5: ='Income Statement'!H13 | I5: ='Income Statement'!I13 | ... P5: ='Income Statement'!P13
A6: Net Income | B6: ='Income Statement'!B18 | C6: ='Income Statement'!C18 | D6: ='Income Statement'!D18 | E6: ='Income Statement'!E18 | F6: ='Income Statement'!F18 | G6: ='Income Statement'!G18 | H6: ='Income Statement'!H18 | I6: ='Income Statement'!I18 | ... P6: ='Income Statement'!P18
A7: Cash from Operations | B7: ='Cash Flow'!B12 | C7: ='Cash Flow'!C12 | D7: ='Cash Flow'!D12 | E7: ='Cash Flow'!E12 | F7: ='Cash Flow'!F12 | G7: ='Cash Flow'!G12 | H7: ='Cash Flow'!H12 | I7: ='Cash Flow'!I12 | ... P7: ='Cash Flow'!P12
A8: CapEx | B8: ='Cash Flow'!B15 | C8: ='Cash Flow'!C15 | D8: ='Cash Flow'!D15 | E8: ='Cash Flow'!E15 | F8: ='Cash Flow'!F15 | G8: ='Cash Flow'!G15 | H8: ='Cash Flow'!H15 | I8: ='Cash Flow'!I15 | ... P8: ='Cash Flow'!P15
A9: Free Cash Flow | B9: ='Cash Flow'!B12+'Cash Flow'!B15 | C9: ='Cash Flow'!C12+'Cash Flow'!C15 | D9: ='Cash Flow'!D12+'Cash Flow'!D15 | E9: ='Cash Flow'!E12+'Cash Flow'!E15 | F9: ='Cash Flow'!F12+'Cash Flow'!F15 | G9: ='Cash Flow'!G12+'Cash Flow'!G15 | H9: ='Cash Flow'!H12+'Cash Flow'!H15 | I9: ='Cash Flow'!I12+'Cash Flow'!I15 | ... P9: ='Cash Flow'!P12+'Cash Flow'!P15
A10: Ending Cash | B10: ='Cash Flow'!B22 | C10: ='Cash Flow'!C22 | D10: ='Cash Flow'!D22 | E10: ='Cash Flow'!E22 | F10: ='Cash Flow'!F22 | G10: ='Cash Flow'!G22 | H10: ='Cash Flow'!H22 | I10: ='Cash Flow'!I22 | ... P10: ='Cash Flow'!P22
A11: Total Assets | B11: ='Balance Sheet'!B12 | C11: ='Balance Sheet'!C12 | D11: ='Balance Sheet'!D12 | E11: ='Balance Sheet'!E12 | F11: ='Balance Sheet'!F12 | G11: ='Balance Sheet'!G12 | H11: ='Balance Sheet'!H12 | I11: ='Balance Sheet'!I12 | ... P11: ='Balance Sheet'!P12
A12: Total Debt | B12: ='Balance Sheet'!B19 | C12: ='Balance Sheet'!C19 | D12: ='Balance Sheet'!D19 | E12: ='Balance Sheet'!E19 | F12: ='Balance Sheet'!F19 | G12: ='Balance Sheet'!G19 | H12: ='Balance Sheet'!H19 | I12: ='Balance Sheet'!I19 | ... P12: ='Balance Sheet'!P19
A13: Total Equity | B13: ='Balance Sheet'!B26 | C13: ='Balance Sheet'!C26 | D13: ='Balance Sheet'!D26 | E13: ='Balance Sheet'!E26 | F13: ='Balance Sheet'!F26 | G13: ='Balance Sheet'!G26 | H13: ='Balance Sheet'!H26 | I13: ='Balance Sheet'!I26 | ... P13: ='Balance Sheet'!P26
A14: Gross Margin % | B14: ='Income Statement'!B20 | C14: ='Income Statement'!C20 | D14: ='Income Statement'!D20 | E14: ='Income Statement'!E20 | F14: ='Income Statement'!F20 | G14: ='Income Statement'!G20 | H14: ='Income Statement'!H20 | I14: ='Income Statement'!I20 | ... P14: ='Income Statement'!P20
A15: Net Margin % | B15: ='Income Statement'!B22 | C15: ='Income Statement'!C22 | D15: ='Income Statement'!D22 | E15: ='Income Statement'!E22 | F15: ='Income Statement'!F22 | G15: ='Income Statement'!G22 | H15: ='Income Statement'!H22 | I15: ='Income Statement'!I22 | ... P15: ='Income Statement'!P22
A16: Debt / Equity | B16: ='Balance Sheet'!B19/'Balance Sheet'!B26 | C16: ='Balance Sheet'!C19/'Balance Sheet'!C26 | D16: ='Balance Sheet'!D19/'Balance Sheet'!D26 | E16: ='Balance Sheet'!E19/'Balance Sheet'!E26 | F16: ='Balance Sheet'!F19/'Balance Sheet'!F26 | G16: ='Balance Sheet'!G19/'Balance Sheet'!G26 | H16: ='Balance Sheet'!H19/'Balance Sheet'!H26 | I16: ='Balance Sheet'!I19/'Balance Sheet'!I26 | ... P16: ='Balance Sheet'!P19/'Balance Sheet'!P26

Sheet Income Statement
A2: USD (thousands) | B2: 2024 | C2: 2025 | D2: 2026 | E2: 2027 | F2: 2028 | G2: 2029 | H2: 2030 | I2: 2031 | J2: 2032 | K2: 2033 | L2: 2034 | M2: 2035 | N2: 2036 | O2: 2037 | P2: 2038
A3: REVENUE
A4: Net Revenue | B4: 50000 | C4: =B4*(1+0.08) | D4: =C4*(1+0.08) | E4: =D4*(1+0.08) | F4: =E4*(1+0.08) | G4: =F4*(1+0.08) | H4: =G4*(1+0.08) | I4: =H4*(1+0.08) | J4: =I4*(1+0.08) | ... P4: =O4*(1+0.08)
A5: COST OF GOODS SOLD
A6: Cost of Goods Sold | B6: =-B4*0.6 | C6: =-C4*0.6 | D6: =-D4*0.6 | E6: =-E4*0.6 | F6: =-F4*0.6 | G6: =-G4*0.6 | H6: =-H4*0.6 | I6: =-I4*0.6 | ... P6: =-P4*0.6
A7: Gross Profit | B7: =B4+B6 | C7: =C4+C6 | D7: =D4+D6 | E7: =E4+E6 | F7: =F4+F6 | G7: =G4+G6 | H7: =H4+H6 | I7: =I4+I6 | ... P7: =P4+P6
A8: OPERATING EXPENSES
A9: Research & Development | B9: =-B4*0.08 | C9: =-C4*0.08 | D9: =-D4*0.08 | E9: =-E4*0.08 | F9: =-F4*0.08 | G9: =-G4*0.08 | H9: =-H4*0.08 | I9: =-I4*0.08 | ... P9: =-P4*0.08
A10: Selling, General & Admin | B10: =-B4*0.12 | C10: =-C4*0.12 | D10: =-D4*0.12 | E10: =-E4*0.12 | F10: =-F4*0.12 | G10: =-G4*0.12 | H10: =-H4*0.12 | I10: =-I4*0.12 | ... P10: =-P4*0.12
A11: Depreciation & Amortisation | B11: =-B4*0.05 | C11: =-C4*0.05 | D11: =-D4*0.05 | E11: =-E4*0.05 | F11: =-F4*0.05 | G11: =-G4*0.05 | H11: =-H4*0.05 | I11: =-I4*0.05 | ... P11: =-P4*0.05
A12: Total Operating Expenses | B12: =SUM(B9:B11) | C12: =SUM(C9:C11) | D12: =SUM(D9:D11) | E12: =SUM(E9:E11) | F12: =SUM(F9:F11) | G12: =SUM(G9:G11) | H12: =SUM(H9:H11) | I12: =SUM(I9:I11) | ... P12: =SUM(P9:P11)
A13: Operating Income (EBIT) | B13: =B7+B12 | C13: =C7+C12 | D13: =D7+D12 | E13: =E7+E12 | F13: =F7+F12 | G13: =G7+G12 | H13: =H7+H12 | I13: =I7+I12 | ... P13: =P7+P12
A14: BELOW THE LINE
A15: Interest Expense | B15: =-20000*0.05 | C15: =-'Balance Sheet'!B19*0.05 | D15: =-'Balance Sheet'!C19*0.05 | E15: =-'Balance Sheet'!D19*0.05 | F15: =-'Balance Sheet'!E19*0.05 | G15: =-'Balance Sheet'!F19*0.05 | H15: =-'Balance Sheet'!G19*0.05 | I15: =-'Balance Sheet'!H19*0.05 | J15: =-'Balance Sheet'!I19*0.05 | ... P15: =-'Balance Sheet'!O19*0.05
A16: Earnings Before Tax (EBT) | B16: =B13+B15 | C16: =C13+C15 | D16: =D13+D15 | E16: =E13+E15 | F16: =F13+F15 | G16: =G13+G15 | H16: =H13+H15 | I16: =I13+I15 | ... P16: =P13+P15
A17: Income Tax Expense | B17: =-MAX(B16*0.21,0) | C17: =-MAX(C16*0.21,0) | D17: =-MAX(D16*0.21,0) | E17: =-MAX(E16*0.21,0) | F17: =-MAX(F16*0.21,0) | G17: =-MAX(G16*0.21,0) | H17: =-MAX(H16*0.21,0) | I17: =-MAX(I16*0.21,0) | ... P17: =-MAX(P16*0.21,0)
A18: Net Income | B18: =B16+B17 | C18: =C16+C17 | D18: =D16+D17 | E18: =E16+E17 | F18: =F16+F17 | G18: =G16+G17 | H18: =H16+H17 | I18: =I16+I17 | ... P18: =P16+P17
A19: MARGINS
A20: Gross Margin % | B20: =B7/B4 | C20: =C7/C4 | D20: =D7/D4 | E20: =E7/E4 | F20: =F7/F4 | G20: =G7/G4 | H20: =H7/H4 | I20: =I7/I4 | ... P20: =P7/P4
A21: EBIT Margin % | B21: =B13/B4 | C21: =C13/C4 | D21: =D13/D4 | E21: =E13/E4 | F21: =F13/F4 | G21: =G13/G4 | H21: =H13/H4 | I21: =I13/I4 | ... P21: =P13/P4
A22: Net Profit Margin % | B22: =B18/B4 | C22: =C18/C4 | D22: =D18/D4 | E22: =E18/E4 | F22: =F18/F4 | G22: =G18/G4 | H22: =H18/H4 | I22: =I18/I4 | ... P22: =P18/P4

Sheet Balance Sheet
A2: USD (thousands) | B2: 2024 | C2: 2025 | D2: 2026 | E2: 2027 | F2: 2028 | G2: 2029 | H2: 2030 | I2: 2031 | J2: 2032 | K2: 2033 | L2: 2034 | M2: 2035 | N2: 2036 | O2: 2037 | P2: 2038
A3: CURRENT ASSETS
A4: Cash & Equivalents | B4: ='Cash Flow'!B22 | C4: ='Cash Flow'!C22 | D4: ='Cash Flow'!D22 | E4: ='Cash Flow'!E22 | F4: ='Cash Flow'!F22 | G4: ='Cash Flow'!G22 | H4: ='Cash Flow'!H22 | I4: ='Cash Flow'!I22 | ... P4: ='Cash Flow'!P22
A5: Accounts Receivable | B5: ='Income Statement'!B4*0.08 | C5: ='Income Statement'!C4*0.08 | D5: ='Income Statement'!D4*0.08 | E5: ='Income Statement'!E4*0.08 | F5: ='Income Statement'!F4*0.08 | G5: ='Income Statement'!G4*0.08 | H5: ='Income Statement'!H4*0.08 | I5: ='Income Statement'!I4*0.08 | ... P5: ='Income Statement'!P4*0.08
A6: Inventory | B6: ='Income Statement'!B4*0.06 | C6: ='Income Statement'!C4*0.06 | D6: ='Income Statement'!D4*0.06 | E6: ='Income Statement'!E4*0.06 | F6: ='Income Statement'!F4*0.06 | G6: ='Income Statement'!G4*0.06 | H6: ='Income Statement'!H4*0.06 | I6: ='Income Statement'!I4*0.06 | ... P6: ='Income Statement'!P4*0.06
A7: Total Current Assets | B7: =SUM(B4:B6) | C7: =SUM(C4:C6) | D7: =SUM(D4:D6) | E7: =SUM(E4:E6) | F7: =SUM(F4:F6) | G7: =SUM(G4:G6) | H7: =SUM(H4:H6) | I7: =SUM(I4:I6) | ... P7: =SUM(P4:P6)
A8: NON-CURRENT ASSETS
A9: Property, Plant & Equipment (net) | B9: =15000+'Cash Flow'!B18-'Income Statement'!B11 | C9: =B9+'Cash Flow'!C18-'Income Statement'!C11 | D9: =C9+'Cash Flow'!D18-'Income Statement'!D11 | E9: =D9+'Cash Flow'!E18-'Income Statement'!E11 | F9: =E9+'Cash Flow'!F18-'Income Statement'!F11 | G9: =F9+'Cash Flow'!G18-'Income Statement'!G11 | H9: =G9+'Cash Flow'!H18-'Income Statement'!H11 | I9: =H9+'Cash Flow'!I18-'Income Statement'!I11 | J9: =I9+'Cash Flow'!J18-'Income Statement'!J11 | ... P9: =O9+'Cash Flow'!P18-'Income Statement'!P11
A10: Intangibles & Goodwill | B10: 2000 | C10: 2000 | D10: 2000 | E10: 2000 | F10: 2000 | G10: 2000 | H10: 2000 | I10: 2000 | J10: 2000 | K10: 2000 | L10: 2000 | M10: 2000 | N10: 2000 | O10: 2000 | P10: 2000
A11: Total Non-Current Assets | B11: =SUM(B9:B10) | C11: =SUM(C9:C10) | D11: =SUM(D9:D10) | E11: =SUM(E9:E10) | F11: =SUM(F9:F10) | G11: =SUM(G9:G10) | H11: =SUM(H9:H10) | I11: =SUM(I9:I10) | ... P11: =SUM(P9:P10)
A12: TOTAL ASSETS | B12: =B7+B11 | C12: =C7+C11 | D12: =D7+D11 | E12: =E7+E11 | F12: =F7+F11 | G12: =G7+G11 | H12: =H7+H11 | I12: =I7+I11 | ... P12: =P7+P11
A14: CURRENT LIABILITIES
A15: Accounts Payable | B15: ='Income Statement'!B6*(-0.25) | C15: ='Income Statement'!C6*(-0.25) | D15: ='Income Statement'!D6*(-0.25) | E15: ='Income Statement'!E6*(-0.25) | F15: ='Income Statement'!F6*(-0.25) | G15: ='Income Statement'!G6*(-0.25) | H15: ='Income Statement'!H6*(-0.25) | I15: ='Income Statement'!I6*(-0.25) | ... P15: ='Income Statement'!P6*(-0.25)
A16: Accrued Liabilities | B16: ='Income Statement'!B4*0.03 | C16: ='Income Statement'!C4*0.03 | D16: ='Income Statement'!D4*0.03 | E16: ='Income Statement'!E4*0.03 | F16: ='Income Statement'!F4*0.03 | G16: ='Income Statement'!G4*0.03 | H16: ='Income Statement'!H4*0.03 | I16: ='Income Statement'!I4*0.03 | ... P16: ='Income Statement'!P4*0.03
A17: Total Current Liabilities | B17: =SUM(B15:B16) | C17: =SUM(C15:C16) | D17: =SUM(D15:D16) | E17: =SUM(E15:E16) | F17: =SUM(F15:F16) | G17: =SUM(G15:G16) | H17: =SUM(H15:H16) | I17: =SUM(I15:I16) | ... P17: =SUM(P15:P16)
A18: NON-CURRENT LIABILITIES
A19: Long-Term Debt | B19: 19000 | C19: =MAX(B19-1000,0) | D19: =MAX(C19-1000,0) | E19: =MAX(D19-1000,0) | F19: =MAX(E19-1000,0) | G19: =MAX(F19-1000,0) | H19: =MAX(G19-1000,0) | I19: =MAX(H19-1000,0) | J19: =MAX(I19-1000,0) | ... P19: =MAX(O19-1000,0)
A20: Total Non-Current Liabilities | B20: =B19 | C20: =C19 | D20: =D19 | E20: =E19 | F20: =F19 | G20: =G19 | H20: =H19 | I20: =I19 | ... P20: =P19
A21: TOTAL LIABILITIES | B21: =B17+B20 | C21: =C17+C20 | D21: =D17+D20 | E21: =E17+E20 | F21: =F17+F20 | G21: =G17+G20 | H21: =H17+H20 | I21: =I17+I20 | ... P21: =P17+P20
A23: SHAREHOLDERS' EQUITY
A24: Paid-In Capital | B24: =B12-B21-B25 | C24: =C12-C21-C25 | D24: =D12-D21-D25 | E24: =E12-E21-E25 | F24: =F12-F21-F25 | G24: =G12-G21-G25 | H24: =H12-H21-H25 | I24: =I12-I21-I25 | ... P24: =P12-P21-P25
A25: Retained Earnings | B25: ='Income Statement'!B18*(1-0.3) | C25: =B25+'Income Statement'!C18*(1-0.3) | D25: =C25+'Income Statement'!D18*(1-0.3) | E25: =D25+'Income Statement'!E18*(1-0.3) | F25: =E25+'Income Statement'!F18*(1-0.3) | G25: =F25+'Income Statement'!G18*(1-0.3) | H25: =G25+'Income Statement'!H18*(1-0.3) | I25: =H25+'Income Statement'!I18*(1-0.3) | J25: =I25+'Income Statement'!J18*(1-0.3) | ... P25: =O25+'Income Statement'!P18*(1-0.3)
A26: TOTAL EQUITY | B26: =B24+B25 | C26: =C24+C25 | D26: =D24+D25 | E26: =E24+E25 | F26: =F24+F25 | G26: =G24+G25 | H26: =H24+H25 | I26: =I24+I25 | ... P26: =P24+P25
A28: TOTAL LIABILITIES & EQUITY | B28: =B21+B26 | C28: =C21+C26 | D28: =D21+D26 | E28: =E21+E26 | F28: =F21+F26 | G28: =G21+G26 | H28: =H21+H26 | I28: =I21+I26 | ... P28: =P21+P26
A29: BALANCE CHECK (Assets = Liabilities + Equity)
B30: =IF(ABS(B12-B28)<1,"OK","MISMATCH") | C30: =IF(ABS(C12-C28)<1,"OK","MISMATCH") | D30: =IF(ABS(D12-D28)<1,"OK","MISMATCH") | E30: =IF(ABS(E12-E28)<1,"OK","MISMATCH") | F30: =IF(ABS(F12-F28)<1,"OK","MISMATCH") | G30: =IF(ABS(G12-G28)<1,"OK","MISMATCH") | H30: =IF(ABS(H12-H28)<1,"OK","MISMATCH") | I30: =IF(ABS(I12-I28)<1,"OK","MISMATCH") | ... P30: =IF(ABS(P12-P28)<1,"OK","MISMATCH")

Sheet Cash Flow
A2: USD (thousands) | B2: 2024 | C2: 2025 | D2: 2026 | E2: 2027 | F2: 2028 | G2: 2029 | H2: 2030 | I2: 2031 | J2: 2032 | K2: 2033 | L2: 2034 | M2: 2035 | N2: 2036 | O2: 2037 | P2: 2038
A3: OPERATING ACTIVITIES
A4: Net Income | B4: ='Income Statement'!B18 | C4: ='Income Statement'!C18 | D4: ='Income Statement'!D18 | E4: ='Income Statement'!E18 | F4: ='Income Statement'!F18 | G4: ='Income Statement'!G18 | H4: ='Income Statement'!H18 | I4: ='Income Statement'!I18 | ... P4: ='Income Statement'!P18
A5: Add: D&A | B5: =-'Income Statement'!B11 | C5: =-'Income Statement'!C11 | D5: =-'Income Statement'!D11 | E5: =-'Income Statement'!E11 | F5: =-'Income Statement'!F11 | G5: =-'Income Statement'!G11 | H5: =-'Income Statement'!H11 | I5: =-'Income Statement'!I11 | ... P5: =-'Income Statement'!P11
A6: Changes in Working Capital
A7: Δ Accounts Receivable | B7: 0 | C7: =-('Balance Sheet'!C5-'Balance Sheet'!B5) | D7: =-('Balance Sheet'!D5-'Balance Sheet'!C5) | E7: =-('Balance Sheet'!E5-'Balance Sheet'!D5) | F7: =-('Balance Sheet'!F5-'Balance Sheet'!E5) | G7: =-('Balance Sheet'!G5-'Balance Sheet'!F5) | H7: =-('Balance Sheet'!H5-'Balance Sheet'!G5) | I7: =-('Balance Sheet'!I5-'Balance Sheet'!H5) | J7: =-('Balance Sheet'!J5-'Balance Sheet'!I5) | ... P7: =-('Balance Sheet'!P5-'Balance Sheet'!O5)
A8: Δ Inventory | B8: 0 | C8: =-('Balance Sheet'!C6-'Balance Sheet'!B6) | D8: =-('Balance Sheet'!D6-'Balance Sheet'!C6) | E8: =-('Balance Sheet'!E6-'Balance Sheet'!D6) | F8: =-('Balance Sheet'!F6-'Balance Sheet'!E6) | G8: =-('Balance Sheet'!G6-'Balance Sheet'!F6) | H8: =-('Balance Sheet'!H6-'Balance Sheet'!G6) | I8: =-('Balance Sheet'!I6-'Balance Sheet'!H6) | J8: =-('Balance Sheet'!J6-'Balance Sheet'!I6) | ... P8: =-('Balance Sheet'!P6-'Balance Sheet'!O6)
A9: Δ Accounts Payable | B9: 0 | C9: ='Balance Sheet'!C15-'Balance Sheet'!B15 | D9: ='Balance Sheet'!D15-'Balance Sheet'!C15 | E9: ='Balance Sheet'!E15-'Balance Sheet'!D15 | F9: ='Balance Sheet'!F15-'Balance Sheet'!E15 | G9: ='Balance Sheet'!G15-'Balance Sheet'!F15 | H9: ='Balance Sheet'!H15-'Balance Sheet'!G15 | I9: ='Balance Sheet'!I15-'Balance Sheet'!H15 | J9: ='Balance Sheet'!J15-'Balance Sheet'!I15 | ... P9: ='Balance Sheet'!P15-'Balance Sheet'!O15
A10: Δ Accrued Liabilities | B10: 0 | C10: ='Balance Sheet'!C16-'Balance Sheet'!B16 | D10: ='Balance Sheet'!D16-'Balance Sheet'!C16 | E10: ='Balance Sheet'!E16-'Balance Sheet'!D16 | F10: ='Balance Sheet'!F16-'Balance Sheet'!E16 | G10: ='Balance Sheet'!G16-'Balance Sheet'!F16 | H10: ='Balance Sheet'!H16-'Balance Sheet'!G16 | I10: ='Balance Sheet'!I16-'Balance Sheet'!H16 | J10: ='Balance Sheet'!J16-'Balance Sheet'!I16 | ... P10: ='Balance Sheet'!P16-'Balance Sheet'!O16
A11: Total Changes in Working Capital | B11: =SUM(B7:B10) | C11: =SUM(C7:C10) | D11: =SUM(D7:D10) | E11: =SUM(E7:E10) | F11: =SUM(F7:F10) | G11: =SUM(G7:G10) | H11: =SUM(H7:H10) | I11: =SUM(I7:I10) | ... P11: =SUM(P7:P10)
A12: Cash from Operations | B12: =SUM(B4:B5)+B11 | C12: =SUM(C4:C5)+C11 | D12: =SUM(D4:D5)+D11 | E12: =SUM(E4:E5)+E11 | F12: =SUM(F4:F5)+F11 | G12: =SUM(G4:G5)+G11 | H12: =SUM(H4:H5)+H11 | I12: =SUM(I4:I5)+I11 | ... P12: =SUM(P4:P5)+P11
A14: INVESTING ACTIVITIES
A15: Capital Expenditures (CapEx) | B15: =-'Income Statement'!B4*0.07 | C15: =-'Income Statement'!C4*0.07 | D15: =-'Income Statement'!D4*0.07 | E15: =-'Income Statement'!E4*0.07 | F15: =-'Income Statement'!F4*0.07 | G15: =-'Income Statement'!G4*0.07 | H15: =-'Income Statement'!H4*0.07 | I15: =-'Income Statement'!I4*0.07 | ... P15: =-'Income Statement'!P4*0.07
A16: Cash from Investing | B16: =B15 | C16: =C15 | D16: =D15 | E16: =E15 | F16: =F15 | G16: =G15 | H16: =H15 | I16: =I15 | ... P16: =P15
A18: FINANCING ACTIVITIES
A19: Debt Repayment | B19: -1000 | C19: -1000 | D19: -1000 | E19: -1000 | F19: -1000 | G19: -1000 | H19: -1000 | I19: -1000 | J19: -1000 | K19: -1000 | L19: -1000 | M19: -1000 | N19: -1000 | O19: -1000 | P19: -1000
A20: Dividends Paid | B20: =-'Income Statement'!B18*0.3 | C20: =-'Income Statement'!C18*0.3 | D20: =-'Income Statement'!D18*0.3 | E20: =-'Income Statement'!E18*0.3 | F20: =-'Income Statement'!F18*0.3 | G20: =-'Income Statement'!G18*0.3 | H20: =-'Income Statement'!H18*0.3 | I20: =-'Income Statement'!I18*0.3 | ... P20: =-'Income Statement'!P18*0.3
A21: Cash from Financing | B21: =SUM(B19:B20) | C21: =SUM(C19:C20) | D21: =SUM(D19:D20) | E21: =SUM(E19:E20) | F21: =SUM(F19:F20) | G21: =SUM(G19:G20) | H21: =SUM(H19:H20) | I21: =SUM(I19:I20) | ... P21: =SUM(P19:P20)
A22: Ending Cash Balance | B22: =B24+B25 | C22: =C24+C25 | D22: =D24+D25 | E22: =E24+E25 | F22: =F24+F25 | G22: =G24+G25 | H22: =H24+H25 | I22: =I24+I25 | ... P22: =P24+P25
A23: NET CASH POSITION
A24: Beginning Cash Balance | B24: 5000 | C24: =B22 | D24: =C22 | E24: =D22 | F24: =E22 | G24: =F22 | H24: =G22 | I24: =H22 | J24: =I22 | ... P24: =O22
A25: Net Change in Cash | B25: =B12+B16+B21 | C25: =C12+C16+C21 | D25: =D12+D16+D21 | E25: =E12+E16+E21 | F25: =F12+F16+F21 | G25: =G12+G16+G21 | H25: =H12+H16+H21 | I25: =I12+I16+I21 | ... P25: =P12+P16+P21
